categories/__init__.py
categories/admin.py
categories/apps.py
categories/base.py
categories/fields.py
categories/genericcollection.py
categories/migration.py
categories/models.py
categories/registration.py
categories/settings.py
categories/urls.py
categories/utils.py
categories/views.py
categories/api/__init__.py
categories/editor/__init__.py
categories/editor/models.py
categories/editor/settings.py
categories/editor/tree_editor.py
categories/editor/utils.py
categories/editor/locale/de/LC_MESSAGES/django.mo
categories/editor/locale/de/LC_MESSAGES/django.po
categories/editor/static/editor/jquery.treeTable.css
categories/editor/static/editor/jquery.treeTable.js
categories/editor/static/editor/toggle-collapse-dark.png
categories/editor/static/editor/toggle-collapse-light.png
categories/editor/static/editor/toggle-expand-dark.png
categories/editor/static/editor/toggle-expand-light.png
categories/editor/templates/admin/editor/grappelli_tree_editor.html
categories/editor/templates/admin/editor/grappelli_tree_list_results.html
categories/editor/templates/admin/editor/tree_editor.html
categories/editor/templates/admin/editor/tree_list_results.html
categories/editor/templatetags/__init__.py
categories/editor/templatetags/admin_tree_list_tags.py
categories/fixtures/categories.json
categories/fixtures/genres.txt
categories/fixtures/musicgenres.json
categories/fixtures/test_category_spaces.txt
categories/fixtures/test_category_tabs.txt
categories/locale/de/LC_MESSAGES/django.mo
categories/locale/de/LC_MESSAGES/django.po
categories/locale/fr/LC_MESSAGES/django.mo
categories/locale/fr/LC_MESSAGES/django.po
categories/locale/it/LC_MESSAGES/django.mo
categories/locale/it/LC_MESSAGES/django.po
categories/management/__init__.py
categories/management/commands/__init__.py
categories/management/commands/add_category_fields.py
categories/management/commands/drop_category_field.py
categories/management/commands/import_categories.py
categories/migrations/0001_initial.py
django_categories-2.0.0.dist-info/LICENSE.txt
django_categories-2.0.0.dist-info/METADATA
django_categories-2.0.0.dist-info/NOTICES.txt
django_categories-2.0.0.dist-info/WHEEL
django_categories-2.0.0.dist-info/top_level.txt
django_categories-2.0.0.dist-info/RECORD
