Metadata-Version: 2.1
Name: django-categories
Version: 2.0.0
Summary: A way to handle one or more hierarchical category trees in django.
Home-page: http://github.com/jazzband/django-categories
Author: Corey Oordt
Author-email: coreyoordt@gmail.com
Classifier: Framework :: Django
License-File: LICENSE.txt
License-File: NOTICES.txt
Requires-Dist: django-mptt
